django_config_initializer_dev/__init__.py
django_config_initializer_dev/config_initializer_dev.py
django_config_initializer_dev-1.0.11.0.dist-info/LICENSE
django_config_initializer_dev-1.0.11.0.dist-info/METADATA
django_config_initializer_dev-1.0.11.0.dist-info/WHEEL
django_config_initializer_dev-1.0.11.0.dist-info/top_level.txt
django_config_initializer_dev-1.0.11.0.dist-info/RECORD
